{
  "id": "https://ror.org/04adarv34",
  "name": "Institut für digitale Gesundheitsdaten Rheinland-Pfalz",
  "email_address": null,
  "ip_addresses": [],
  "established": 2016,
  "types": [
    "Nonprofit"
  ],
  "relationships": [],
  "addresses": [
    {
      "lat": 49.98419,
      "lng": 8.2791,
      "state": null,
      "state_code": null,
      "city": "Mainz",
      "geonames_city": {
        "id": 2874225,
        "city": "Mainz",
        "geonames_admin1": {
          "ascii_name": null,
          "code": null,
          "id": null,
          "name": null
        },
        "geonames_admin2": {
          "ascii_name": null,
          "code": null,
          "id": null,
          "name": null
        },
        "license": {
          "attribution": "Data from geonames.org under a CC-BY 3.0 license",
          "license": "http://creativecommons.org/licenses/by/3.0/"
        },
        "nuts_level1": {
          "code": null,
          "name": null
        },
        "nuts_level2": {
          "code": null,
          "name": null
        },
        "nuts_level3": {
          "code": null,
          "name": null
        }
      },
      "postcode": null,
      "primary": false,
      "line": null,
      "country_geonames_id": null
    }
  ],
  "links": [
    "https://www.idg-rlp.de"
  ],
  "aliases": [
    "Institute for Digital Health Data Rhineland-Patlatinate"
  ],
  "acronyms": [
    "IDG RLP"
  ],
  "status": "active",
  "wikipedia_url": null,
  "labels": [],
  "country": {
    "country_name": "Germany",
    "country_code": "DE"
  },
  "external_ids": {}
}