{
  "id": "https://ror.org/012f7tj07",
  "name": "Telefónica (Spain)",
  "email_address": null,
  "ip_addresses": [],
  "established": 1924,
  "types": [
    "Company"
  ],
  "relationships": [
    {
      "label": "Telefonica (Germany)",
      "type": "Child",
      "id": "https://ror.org/00xfdbb04"
    },
    {
      "label": "Telefónica (United Kingdom)",
      "type": "Child",
      "id": "https://ror.org/00v9tt762"
    }
  ],
  "addresses": [
    {
      "lat": 40.4165,
      "lng": -3.70256,
      "state": null,
      "state_code": null,
      "city": "Madrid",
      "geonames_city": {
        "id": 3117735,
        "city": "Madrid",
        "geonames_admin1": {
          "ascii_name": null,
          "code": null,
          "id": null,
          "name": null
        },
        "geonames_admin2": {
          "ascii_name": null,
          "code": null,
          "id": null,
          "name": null
        },
        "license": {
          "attribution": "Data from geonames.org under a CC-BY 3.0 license",
          "license": "http://creativecommons.org/licenses/by/3.0/"
        },
        "nuts_level1": {
          "code": null,
          "name": null
        },
        "nuts_level2": {
          "code": null,
          "name": null
        },
        "nuts_level3": {
          "code": null,
          "name": null
        }
      },
      "postcode": null,
      "primary": false,
      "line": null,
      "country_geonames_id": null
    }
  ],
  "links": [
    "https://www.telefonica.com/es/"
  ],
  "aliases": [],
  "acronyms": [],
  "status": "active",
  "wikipedia_url": "https://en.wikipedia.org/wiki/Telef%C3%B3nica",
  "labels": [],
  "country": {
    "country_name": "Spain",
    "country_code": "ES"
  },
  "external_ids": {
    "GRID": {
      "all": "grid.426313.1",
      "preferred": "grid.426313.1"
    },
    "ISNI": {
      "all": [
        "0000 0004 0630 219X"
      ],
      "preferred": null
    },
    "Wikidata": {
      "all": [
        "Q160229"
      ],
      "preferred": null
    }
  }
}