{
  "id": "https://ror.org/01kq2by19",
  "name": "Fukushima Institute for Research, Education and Innovation",
  "email_address": null,
  "ip_addresses": [],
  "established": 2023,
  "types": [
    "Education"
  ],
  "relationships": [],
  "addresses": [
    {
      "lat": 37.48333,
      "lng": 141,
      "state": null,
      "state_code": null,
      "city": "Namie",
      "geonames_city": {
        "id": 2111704,
        "city": "Namie",
        "geonames_admin1": {
          "ascii_name": null,
          "code": "JP.07",
          "id": null,
          "name": "Fukushima"
        },
        "geonames_admin2": {
          "ascii_name": null,
          "code": null,
          "id": null,
          "name": null
        },
        "license": {
          "attribution": "Data from geonames.org under a CC-BY 3.0 license",
          "license": "http://creativecommons.org/licenses/by/3.0/"
        },
        "nuts_level1": {
          "code": null,
          "name": null
        },
        "nuts_level2": {
          "code": null,
          "name": null
        },
        "nuts_level3": {
          "code": null,
          "name": null
        }
      },
      "postcode": null,
      "primary": false,
      "line": null,
      "country_geonames_id": null
    }
  ],
  "links": [
    "https://www.f-rei.go.jp"
  ],
  "aliases": [
    "福島国際研究教育機構"
  ],
  "acronyms": [
    "F-REI"
  ],
  "status": "active",
  "wikipedia_url": null,
  "labels": [],
  "country": {
    "country_name": "Japan",
    "country_code": "JP"
  },
  "external_ids": {}
}