{
  "id": "https://ror.org/017kqh787",
  "name": "OxyMem (Ireland)",
  "email_address": null,
  "ip_addresses": [],
  "established": 1914,
  "types": [
    "Company"
  ],
  "relationships": [],
  "addresses": [
    {
      "lat": 53.42278,
      "lng": -7.93722,
      "state": null,
      "state_code": null,
      "city": "Athlone",
      "geonames_city": {
        "id": 3313472,
        "city": "Athlone",
        "geonames_admin1": {
          "ascii_name": null,
          "code": null,
          "id": null,
          "name": null
        },
        "geonames_admin2": {
          "ascii_name": null,
          "code": null,
          "id": null,
          "name": null
        },
        "license": {
          "attribution": "Data from geonames.org under a CC-BY 3.0 license",
          "license": "http://creativecommons.org/licenses/by/3.0/"
        },
        "nuts_level1": {
          "code": null,
          "name": null
        },
        "nuts_level2": {
          "code": null,
          "name": null
        },
        "nuts_level3": {
          "code": null,
          "name": null
        }
      },
      "postcode": null,
      "primary": false,
      "line": null,
      "country_geonames_id": null
    }
  ],
  "links": [
    "https://oxymem.com"
  ],
  "aliases": [],
  "acronyms": [],
  "status": "active",
  "wikipedia_url": null,
  "labels": [],
  "country": {
    "country_name": "Ireland",
    "country_code": "IE"
  },
  "external_ids": {
    "GRID": {
      "all": "grid.496860.5",
      "preferred": "grid.496860.5"
    }
  }
}