{
  "id": "https://ror.org/05p85rs79",
  "name": "Ohio Department of Natural Resources",
  "email_address": null,
  "ip_addresses": [],
  "established": 1949,
  "types": [
    "Government"
  ],
  "relationships": [
    {
      "label": "Ohio Division of Geological Survey",
      "type": "Child",
      "id": "https://ror.org/035cp7g76"
    }
  ],
  "addresses": [
    {
      "lat": 39.96118,
      "lng": -82.99879,
      "state": null,
      "state_code": null,
      "city": "Columbus",
      "geonames_city": {
        "id": 4509177,
        "city": "Columbus",
        "geonames_admin1": {
          "ascii_name": null,
          "code": null,
          "id": null,
          "name": null
        },
        "geonames_admin2": {
          "ascii_name": null,
          "code": null,
          "id": null,
          "name": null
        },
        "license": {
          "attribution": "Data from geonames.org under a CC-BY 3.0 license",
          "license": "http://creativecommons.org/licenses/by/3.0/"
        },
        "nuts_level1": {
          "code": null,
          "name": null
        },
        "nuts_level2": {
          "code": null,
          "name": null
        },
        "nuts_level3": {
          "code": null,
          "name": null
        }
      },
      "postcode": null,
      "primary": false,
      "line": null,
      "country_geonames_id": null
    }
  ],
  "links": [
    "http://ohiodnr.gov/"
  ],
  "aliases": [],
  "acronyms": [
    "ODNR"
  ],
  "status": "active",
  "wikipedia_url": "https://en.wikipedia.org/wiki/Ohio_Department_of_Natural_Resources",
  "labels": [],
  "country": {
    "country_name": "United States",
    "country_code": "US"
  },
  "external_ids": {
    "GRID": {
      "all": "grid.448528.7",
      "preferred": "grid.448528.7"
    },
    "ISNI": {
      "all": [
        "0000 0001 0193 8373"
      ],
      "preferred": null
    },
    "Wikidata": {
      "all": [
        "Q7080799"
      ],
      "preferred": null
    }
  }
}