{
  "id": "https://ror.org/040x95d02",
  "name": "Nabarangpur College",
  "email_address": null,
  "ip_addresses": [],
  "established": 1971,
  "types": [
    "Government"
  ],
  "relationships": [],
  "addresses": [
    {
      "lat": 19.2333,
      "lng": 82.55,
      "state": null,
      "state_code": null,
      "city": "Nabarangapur District",
      "geonames_city": {
        "id": 8908677,
        "city": "Nabarangapur District",
        "geonames_admin1": {
          "ascii_name": null,
          "code": "IN.OD",
          "id": null,
          "name": "Odisha"
        },
        "geonames_admin2": {
          "ascii_name": null,
          "code": null,
          "id": null,
          "name": null
        },
        "license": {
          "attribution": "Data from geonames.org under a CC-BY 3.0 license",
          "license": "http://creativecommons.org/licenses/by/3.0/"
        },
        "nuts_level1": {
          "code": null,
          "name": null
        },
        "nuts_level2": {
          "code": null,
          "name": null
        },
        "nuts_level3": {
          "code": null,
          "name": null
        }
      },
      "postcode": null,
      "primary": false,
      "line": null,
      "country_geonames_id": null
    }
  ],
  "links": [
    "https://nabarangpurcollege.ac.in"
  ],
  "aliases": [],
  "acronyms": [],
  "status": "active",
  "wikipedia_url": null,
  "labels": [
    {
      "label": "ନବରଙ୍ଗପୁର ମହାବିଦ୍ୟାଳୟ",
      "iso639": "or"
    }
  ],
  "country": {
    "country_name": "India",
    "country_code": "IN"
  },
  "external_ids": {}
}