{
  "id": "https://ror.org/04yn30r61",
  "name": "A P J Abdul Kalam Technological University",
  "email_address": null,
  "ip_addresses": [],
  "established": 2014,
  "types": [
    "Education",
    "Funder"
  ],
  "relationships": [
    {
      "label": "Universal Engineering College",
      "type": "Child",
      "id": "https://ror.org/01hj51r83"
    },
    {
      "label": "KMEA Engineering College",
      "type": "Related",
      "id": "https://ror.org/05m3rf228"
    }
  ],
  "addresses": [
    {
      "lat": 8.4855,
      "lng": 76.94924,
      "state": null,
      "state_code": null,
      "city": "Thiruvananthapuram",
      "geonames_city": {
        "id": 1254163,
        "city": "Thiruvananthapuram",
        "geonames_admin1": {
          "ascii_name": null,
          "code": "IN.KL",
          "id": null,
          "name": "Kerala"
        },
        "geonames_admin2": {
          "ascii_name": null,
          "code": null,
          "id": null,
          "name": null
        },
        "license": {
          "attribution": "Data from geonames.org under a CC-BY 3.0 license",
          "license": "http://creativecommons.org/licenses/by/3.0/"
        },
        "nuts_level1": {
          "code": null,
          "name": null
        },
        "nuts_level2": {
          "code": null,
          "name": null
        },
        "nuts_level3": {
          "code": null,
          "name": null
        }
      },
      "postcode": null,
      "primary": false,
      "line": null,
      "country_geonames_id": null
    }
  ],
  "links": [
    "https://ktu.edu.in/"
  ],
  "aliases": [
    "Kerala Technological University"
  ],
  "acronyms": [
    "KTU"
  ],
  "status": "active",
  "wikipedia_url": "https://en.wikipedia.org/wiki/A_P_J_Abdul_Kalam_Technological_University",
  "labels": [],
  "country": {
    "country_name": "India",
    "country_code": "IN"
  },
  "external_ids": {
    "FundRef": {
      "all": [
        "100007778"
      ],
      "preferred": null
    },
    "GRID": {
      "all": "grid.464509.a",
      "preferred": "grid.464509.a"
    },
    "ISNI": {
      "all": [
        "0000 0004 8002 0991"
      ],
      "preferred": "0000 0004 8002 0991"
    },
    "Wikidata": {
      "all": [
        "Q18387794"
      ],
      "preferred": null
    }
  }
}