{
  "id": "https://ror.org/04zj3ra44",
  "name": "Westmead Institute for Medical Research",
  "email_address": null,
  "ip_addresses": [],
  "established": 1996,
  "types": [
    "Facility",
    "Funder"
  ],
  "relationships": [
    {
      "label": "The University of Sydney",
      "type": "Related",
      "id": "https://ror.org/0384j8v12"
    }
  ],
  "addresses": [
    {
      "lat": -33.86785,
      "lng": 151.20732,
      "state": null,
      "state_code": null,
      "city": "Sydney",
      "geonames_city": {
        "id": 2147714,
        "city": "Sydney",
        "geonames_admin1": {
          "ascii_name": null,
          "code": "AU.NSW",
          "id": null,
          "name": "New South Wales"
        },
        "geonames_admin2": {
          "ascii_name": null,
          "code": null,
          "id": null,
          "name": null
        },
        "license": {
          "attribution": "Data from geonames.org under a CC-BY 3.0 license",
          "license": "http://creativecommons.org/licenses/by/3.0/"
        },
        "nuts_level1": {
          "code": null,
          "name": null
        },
        "nuts_level2": {
          "code": null,
          "name": null
        },
        "nuts_level3": {
          "code": null,
          "name": null
        }
      },
      "postcode": null,
      "primary": false,
      "line": null,
      "country_geonames_id": null
    }
  ],
  "links": [
    "http://www.wmi.org.au/Pages/HomePage.aspx"
  ],
  "aliases": [
    "Westmead Millennium Institute for Medical Research"
  ],
  "acronyms": [
    "WMI"
  ],
  "status": "active",
  "wikipedia_url": "https://en.wikipedia.org/wiki/Westmead_Millennium_Institute_for_Medical_Research",
  "labels": [],
  "country": {
    "country_name": "Australia",
    "country_code": "AU"
  },
  "external_ids": {
    "FundRef": {
      "all": [
        "100008720"
      ],
      "preferred": null
    },
    "GRID": {
      "all": "grid.452919.2",
      "preferred": "grid.452919.2"
    },
    "ISNI": {
      "all": [
        "0000 0001 0436 7430"
      ],
      "preferred": null
    },
    "Wikidata": {
      "all": [
        "Q7989078"
      ],
      "preferred": null
    }
  }
}