{
  "id": "https://ror.org/05mjmsc11",
  "name": "Northern Hospital",
  "email_address": null,
  "ip_addresses": [],
  "established": 1998,
  "types": [
    "Healthcare"
  ],
  "relationships": [
    {
      "label": "Northern Health",
      "type": "Parent",
      "id": "https://ror.org/009k7c907"
    },
    {
      "label": "The University of Melbourne",
      "type": "Related",
      "id": "https://ror.org/01ej9dk98"
    }
  ],
  "addresses": [
    {
      "lat": -33.77271,
      "lng": 151.08184,
      "state": null,
      "state_code": null,
      "city": "Epping",
      "geonames_city": {
        "id": 2167280,
        "city": "Epping",
        "geonames_admin1": {
          "ascii_name": null,
          "code": "AU.NSW",
          "id": null,
          "name": "New South Wales"
        },
        "geonames_admin2": {
          "ascii_name": null,
          "code": null,
          "id": null,
          "name": null
        },
        "license": {
          "attribution": "Data from geonames.org under a CC-BY 3.0 license",
          "license": "http://creativecommons.org/licenses/by/3.0/"
        },
        "nuts_level1": {
          "code": null,
          "name": null
        },
        "nuts_level2": {
          "code": null,
          "name": null
        },
        "nuts_level3": {
          "code": null,
          "name": null
        }
      },
      "postcode": null,
      "primary": false,
      "line": null,
      "country_geonames_id": null
    }
  ],
  "links": [
    "https://www.nh.org.au/location/northern-hospital-epping/"
  ],
  "aliases": [],
  "acronyms": [],
  "status": "active",
  "wikipedia_url": "https://en.wikipedia.org/wiki/The_Northern_Hospital,_Epping",
  "labels": [],
  "country": {
    "country_name": "Australia",
    "country_code": "AU"
  },
  "external_ids": {
    "GRID": {
      "all": "grid.416536.3",
      "preferred": "grid.416536.3"
    },
    "ISNI": {
      "all": [
        "0000 0004 0399 9112"
      ],
      "preferred": null
    },
    "Wikidata": {
      "all": [
        "Q7754368"
      ],
      "preferred": null
    }
  }
}