{
  "id": "https://ror.org/00xhz2q61",
  "name": "Veterans Health Service Medical Center",
  "email_address": null,
  "ip_addresses": [],
  "established": 1953,
  "types": [
    "Healthcare"
  ],
  "relationships": [
    {
      "label": "Ministry of Patriots and Veterans Affairs",
      "type": "Parent",
      "id": "https://ror.org/03qehyx72"
    }
  ],
  "addresses": [
    {
      "lat": 37.566,
      "lng": 126.9784,
      "state": null,
      "state_code": null,
      "city": "Seoul",
      "geonames_city": {
        "id": 1835848,
        "city": "Seoul",
        "geonames_admin1": {
          "ascii_name": null,
          "code": "KR.11",
          "id": null,
          "name": "Seoul"
        },
        "geonames_admin2": {
          "ascii_name": null,
          "code": null,
          "id": null,
          "name": null
        },
        "license": {
          "attribution": "Data from geonames.org under a CC-BY 3.0 license",
          "license": "http://creativecommons.org/licenses/by/3.0/"
        },
        "nuts_level1": {
          "code": null,
          "name": null
        },
        "nuts_level2": {
          "code": null,
          "name": null
        },
        "nuts_level3": {
          "code": null,
          "name": null
        }
      },
      "postcode": null,
      "primary": false,
      "line": null,
      "country_geonames_id": null
    }
  ],
  "links": [
    "https://seoul.bohun.or.kr"
  ],
  "aliases": [
    "Central Veterans Hospital",
    "Seoul Veterans Hospital",
    "VHS Medical Center",
    "서울보훈병원"
  ],
  "acronyms": [],
  "status": "active",
  "wikipedia_url": "https://ko.wikipedia.org/wiki/%EC%A4%91%EC%95%99%EB%B3%B4%ED%9B%88%EB%B3%91%EC%9B%90",
  "labels": [
    {
      "label": "중앙보훈병원",
      "iso639": "ko"
    },
    {
      "label": "한국보훈복지의료공단 보훈병원",
      "iso639": "ko"
    }
  ],
  "country": {
    "country_name": "South Korea",
    "country_code": "KR"
  },
  "external_ids": {
    "GRID": {
      "all": "grid.415531.7",
      "preferred": "grid.415531.7"
    },
    "ISNI": {
      "all": [
        "0000 0004 0647 4717"
      ],
      "preferred": null
    },
    "Wikidata": {
      "all": [
        "Q16099935"
      ],
      "preferred": "Q16099935"
    }
  }
}