{
  "id": "https://ror.org/016tr2327",
  "name": "Boyce Thompson Institute",
  "email_address": null,
  "ip_addresses": [],
  "established": 1920,
  "types": [
    "Facility",
    "Funder"
  ],
  "relationships": [],
  "addresses": [
    {
      "lat": 42.44063,
      "lng": -76.49661,
      "state": null,
      "state_code": null,
      "city": "Ithaca",
      "geonames_city": {
        "id": 5122432,
        "city": "Ithaca",
        "geonames_admin1": {
          "ascii_name": null,
          "code": "US.NY",
          "id": null,
          "name": "New York"
        },
        "geonames_admin2": {
          "ascii_name": null,
          "code": null,
          "id": null,
          "name": null
        },
        "license": {
          "attribution": "Data from geonames.org under a CC-BY 3.0 license",
          "license": "http://creativecommons.org/licenses/by/3.0/"
        },
        "nuts_level1": {
          "code": null,
          "name": null
        },
        "nuts_level2": {
          "code": null,
          "name": null
        },
        "nuts_level3": {
          "code": null,
          "name": null
        }
      },
      "postcode": null,
      "primary": false,
      "line": null,
      "country_geonames_id": null
    }
  ],
  "links": [
    "https://btiscience.org"
  ],
  "aliases": [
    "Boyce Thompson Institute for Plant Research"
  ],
  "acronyms": [
    "BTI"
  ],
  "status": "active",
  "wikipedia_url": "https://en.wikipedia.org/wiki/Boyce_Thompson_Institute",
  "labels": [],
  "country": {
    "country_name": "United States",
    "country_code": "US"
  },
  "external_ids": {
    "FundRef": {
      "all": [
        "100007604"
      ],
      "preferred": "100007604"
    },
    "ISNI": {
      "all": [
        "0000 0004 0603 8149"
      ],
      "preferred": "0000 0004 0603 8149"
    },
    "Wikidata": {
      "all": [
        "Q4952261"
      ],
      "preferred": "Q4952261"
    }
  }
}