{
  "id": "https://ror.org/00tgr2h49",
  "name": "Computer Equipment and Technologies",
  "email_address": null,
  "ip_addresses": [],
  "established": 1724,
  "types": [
    "Government"
  ],
  "relationships": [
    {
      "label": "All Russian Institute for Scientific and Technical Information",
      "type": "Child",
      "id": "https://ror.org/047wbzv64"
    },
    {
      "label": "Image Processing Systems Institute",
      "type": "Child",
      "id": "https://ror.org/03134gf68"
    },
    {
      "label": "Institute for Analytical Instrumentation",
      "type": "Child",
      "id": "https://ror.org/02h6vef88"
    },
    {
      "label": "Institute for Design Problems in Microelectronics",
      "type": "Child",
      "id": "https://ror.org/00t7t9a43"
    },
    {
      "label": "Institute for Information Transmission Problems",
      "type": "Child",
      "id": "https://ror.org/013w2d378"
    },
    {
      "label": "Institute of Automation and Electrometry",
      "type": "Child",
      "id": "https://ror.org/05fqdmq12"
    },
    {
      "label": "Institute of Computational Modeling",
      "type": "Child",
      "id": "https://ror.org/047f8bv22"
    },
    {
      "label": "Federal Research Center for Information and Computational Technologies",
      "type": "Child",
      "id": "https://ror.org/02x3mf211"
    },
    {
      "label": "Institute of Informatics Problems",
      "type": "Child",
      "id": "https://ror.org/00n8bqs64"
    },
    {
      "label": "Institute of Microelectronics Technology and High Purity Materials",
      "type": "Child",
      "id": "https://ror.org/034fqtg16"
    },
    {
      "label": "Institute of Physics and Technology",
      "type": "Child",
      "id": "https://ror.org/00x0vxx91"
    },
    {
      "label": "Institute on Laser and Information Technologies",
      "type": "Child",
      "id": "https://ror.org/02jract75"
    },
    {
      "label": "Research Institute for System Studies",
      "type": "Child",
      "id": "https://ror.org/02smvmz76"
    },
    {
      "label": "St. Petersburg Institute for Informatics and Automation",
      "type": "Child",
      "id": "https://ror.org/01ccb9w37"
    },
    {
      "label": "Russian Academy of Sciences",
      "type": "Parent",
      "id": "https://ror.org/05qrfxd25"
    }
  ],
  "addresses": [
    {
      "lat": 55.75222,
      "lng": 37.61556,
      "state": null,
      "state_code": null,
      "city": "Moscow",
      "geonames_city": {
        "id": 524901,
        "city": "Moscow",
        "geonames_admin1": {
          "ascii_name": null,
          "code": "RU.MOW",
          "id": null,
          "name": "Moscow"
        },
        "geonames_admin2": {
          "ascii_name": null,
          "code": null,
          "id": null,
          "name": null
        },
        "license": {
          "attribution": "Data from geonames.org under a CC-BY 3.0 license",
          "license": "http://creativecommons.org/licenses/by/3.0/"
        },
        "nuts_level1": {
          "code": null,
          "name": null
        },
        "nuts_level2": {
          "code": null,
          "name": null
        },
        "nuts_level3": {
          "code": null,
          "name": null
        }
      },
      "postcode": null,
      "primary": false,
      "line": null,
      "country_geonames_id": null
    }
  ],
  "links": [
    "http://ras.ru"
  ],
  "aliases": [],
  "acronyms": [],
  "status": "active",
  "wikipedia_url": null,
  "labels": [],
  "country": {
    "country_name": "Russia",
    "country_code": "RU"
  },
  "external_ids": {
    "GRID": {
      "all": "grid.466114.0",
      "preferred": "grid.466114.0"
    }
  }
}