{
  "id": "https://ror.org/023azs158",
  "name": "ICAR Research Complex for NEH Region",
  "email_address": null,
  "ip_addresses": [],
  "established": 1975,
  "types": [
    "Facility",
    "Funder"
  ],
  "relationships": [
    {
      "label": "Indian Council of Agricultural Research",
      "type": "Parent",
      "id": "https://ror.org/04fw54a43"
    }
  ],
  "addresses": [
    {
      "lat": 25.5,
      "lng": 91.33333,
      "state": null,
      "state_code": null,
      "city": "Meghalaya",
      "geonames_city": {
        "id": 1263207,
        "city": "Meghalaya",
        "geonames_admin1": {
          "ascii_name": null,
          "code": "IN.ML",
          "id": null,
          "name": "Meghalaya"
        },
        "geonames_admin2": {
          "ascii_name": null,
          "code": null,
          "id": null,
          "name": null
        },
        "license": {
          "attribution": "Data from geonames.org under a CC-BY 3.0 license",
          "license": "http://creativecommons.org/licenses/by/3.0/"
        },
        "nuts_level1": {
          "code": null,
          "name": null
        },
        "nuts_level2": {
          "code": null,
          "name": null
        },
        "nuts_level3": {
          "code": null,
          "name": null
        }
      },
      "postcode": null,
      "primary": false,
      "line": null,
      "country_geonames_id": null
    }
  ],
  "links": [
    "https://icar.org.in/node/488"
  ],
  "aliases": [
    "ICAR Research Complex for North Eastern Hill Region"
  ],
  "acronyms": [
    "RCNEH"
  ],
  "status": "active",
  "wikipedia_url": null,
  "labels": [],
  "country": {
    "country_name": "India",
    "country_code": "IN"
  },
  "external_ids": {
    "FundRef": {
      "all": [
        "501100013951"
      ],
      "preferred": "501100013951"
    },
    "GRID": {
      "all": "grid.469932.3",
      "preferred": "grid.469932.3"
    },
    "ISNI": {
      "all": [
        "0000 0001 2203 3565"
      ],
      "preferred": null
    }
  }
}