{
  "id": "https://ror.org/03v0r5n49",
  "name": "Indian Institute of Technology Madras",
  "email_address": null,
  "ip_addresses": [],
  "established": 1959,
  "types": [
    "Facility"
  ],
  "relationships": [
    {
      "label": "Healthcare Technology Innovation Centre",
      "type": "Related",
      "id": "https://ror.org/017mw4x28"
    }
  ],
  "addresses": [
    {
      "lat": 13.08784,
      "lng": 80.27847,
      "state": null,
      "state_code": null,
      "city": "Chennai",
      "geonames_city": {
        "id": 1264527,
        "city": "Chennai",
        "geonames_admin1": {
          "ascii_name": null,
          "code": null,
          "id": null,
          "name": null
        },
        "geonames_admin2": {
          "ascii_name": null,
          "code": null,
          "id": null,
          "name": null
        },
        "license": {
          "attribution": "Data from geonames.org under a CC-BY 3.0 license",
          "license": "http://creativecommons.org/licenses/by/3.0/"
        },
        "nuts_level1": {
          "code": null,
          "name": null
        },
        "nuts_level2": {
          "code": null,
          "name": null
        },
        "nuts_level3": {
          "code": null,
          "name": null
        }
      },
      "postcode": null,
      "primary": false,
      "line": null,
      "country_geonames_id": null
    }
  ],
  "links": [
    "https://www.iitm.ac.in/"
  ],
  "aliases": [
    "IIT Madras"
  ],
  "acronyms": [
    "IITM"
  ],
  "status": "active",
  "wikipedia_url": "http://en.wikipedia.org/wiki/Indian_Institute_of_Technology_Madras",
  "labels": [
    {
      "label": "भारतीय तंत्रज्ञान संस्था",
      "iso639": "mr"
    },
    {
      "label": "भारतीय प्रौद्योगिकी संस्थान मद्रास",
      "iso639": "hi"
    },
    {
      "label": "இந்திய தொழில்நுட்பக் கழகம் சென்னை",
      "iso639": "ta"
    },
    {
      "label": "ఇండియన్ ఇన్ స్టిట్యూట్ ఆఫ్ టెక్నాలజీ మద్రాస్",
      "iso639": "te"
    },
    {
      "label": "ಭಾರತೀಯ ತಂತ್ರಜ್ಞಾನ ಸಂಸ್ಥೆ ಮದ್ರಾಸ್",
      "iso639": "kn"
    },
    {
      "label": "ഇന്ത്യൻ ഇൻസ്റ്റിറ്റ്യൂട്ട് ഓഫ് ടെക്നോളജി മദ്രാസ്",
      "iso639": "ml"
    }
  ],
  "country": {
    "country_name": "India",
    "country_code": "IN"
  },
  "external_ids": {
    "FundRef": {
      "all": [
        "501100003845"
      ],
      "preferred": null
    },
    "GRID": {
      "all": "grid.417969.4",
      "preferred": "grid.417969.4"
    },
    "ISNI": {
      "all": [
        "0000 0001 2315 1926"
      ],
      "preferred": null
    },
    "Wikidata": {
      "all": [
        "Q858662"
      ],
      "preferred": null
    }
  }
}