{
  "id": "https://ror.org/059gw8r13",
  "name": "Xinjiang University",
  "email_address": null,
  "ip_addresses": [],
  "established": 1924,
  "types": [
    "Education"
  ],
  "relationships": [],
  "addresses": [
    {
      "lat": 43.80096,
      "lng": 87.60046,
      "state": null,
      "state_code": null,
      "city": "Ürümqi",
      "geonames_city": {
        "id": 1529102,
        "city": "Ürümqi",
        "geonames_admin1": {
          "ascii_name": null,
          "code": null,
          "id": null,
          "name": null
        },
        "geonames_admin2": {
          "ascii_name": null,
          "code": null,
          "id": null,
          "name": null
        },
        "license": {
          "attribution": "Data from geonames.org under a CC-BY 3.0 license",
          "license": "http://creativecommons.org/licenses/by/3.0/"
        },
        "nuts_level1": {
          "code": null,
          "name": null
        },
        "nuts_level2": {
          "code": null,
          "name": null
        },
        "nuts_level3": {
          "code": null,
          "name": null
        }
      },
      "postcode": null,
      "primary": false,
      "line": null,
      "country_geonames_id": null
    }
  ],
  "links": [
    "https://www.xju.edu.cn"
  ],
  "aliases": [
    "Xīnjiāng Dàxué"
  ],
  "acronyms": [
    "XJU"
  ],
  "status": "active",
  "wikipedia_url": "http://en.wikipedia.org/wiki/Xinjiang_University",
  "labels": [
    {
      "label": "新疆大学",
      "iso639": "zh"
    }
  ],
  "country": {
    "country_name": "China",
    "country_code": "CN"
  },
  "external_ids": {
    "FundRef": {
      "all": [
        "501100008845"
      ],
      "preferred": "501100008845"
    },
    "GRID": {
      "all": "grid.413254.5",
      "preferred": "grid.413254.5"
    },
    "ISNI": {
      "all": [
        "0000 0000 9544 7024"
      ],
      "preferred": null
    },
    "Wikidata": {
      "all": [
        "Q985578"
      ],
      "preferred": null
    }
  }
}