{
  "id": "https://ror.org/056mff334",
  "name": "Centro de Investigação em Educação Básica",
  "email_address": null,
  "ip_addresses": [],
  "established": null,
  "types": [
    "Facility"
  ],
  "relationships": [
    {
      "label": "Polytechnic Institute of Bragança",
      "type": "Parent",
      "id": "https://ror.org/00prsav78"
    }
  ],
  "addresses": [
    {
      "lat": 41.83615,
      "lng": -6.76346,
      "state": null,
      "state_code": null,
      "city": "Bragança",
      "geonames_city": {
        "id": 2742026,
        "city": "Bragança",
        "geonames_admin1": {
          "ascii_name": null,
          "code": "PT.04",
          "id": null,
          "name": "Bragança"
        },
        "geonames_admin2": {
          "ascii_name": null,
          "code": null,
          "id": null,
          "name": null
        },
        "license": {
          "attribution": "Data from geonames.org under a CC-BY 3.0 license",
          "license": "http://creativecommons.org/licenses/by/3.0/"
        },
        "nuts_level1": {
          "code": null,
          "name": null
        },
        "nuts_level2": {
          "code": null,
          "name": null
        },
        "nuts_level3": {
          "code": null,
          "name": null
        }
      },
      "postcode": null,
      "primary": false,
      "line": null,
      "country_geonames_id": null
    }
  ],
  "links": [
    "http://cieb.ese.ipb.pt"
  ],
  "aliases": [
    "Instituto Politécnico de Bragança Centro de Investigação em Educação Básica"
  ],
  "acronyms": [
    "CIEB"
  ],
  "status": "active",
  "wikipedia_url": null,
  "labels": [],
  "country": {
    "country_name": "Portugal",
    "country_code": "PT"
  },
  "external_ids": {
    "ISNI": {
      "all": [
        "0000 0005 1091 4188"
      ],
      "preferred": "0000 0005 1091 4188"
    }
  }
}