{
  "id": "https://ror.org/00n6mjv39",
  "name": "Mahatma Gandhi Arts, Science & Late Nasaruddhinbhai Panjwani Commerce College",
  "email_address": null,
  "ip_addresses": [],
  "established": 1981,
  "types": [
    "Education"
  ],
  "relationships": [],
  "addresses": [
    {
      "lat": 20.46651,
      "lng": 79.98387,
      "state": null,
      "state_code": null,
      "city": "Armori",
      "geonames_city": {
        "id": 1278385,
        "city": "Armori",
        "geonames_admin1": {
          "ascii_name": null,
          "code": "IN.MH",
          "id": null,
          "name": "Maharashtra"
        },
        "geonames_admin2": {
          "ascii_name": null,
          "code": null,
          "id": null,
          "name": null
        },
        "license": {
          "attribution": "Data from geonames.org under a CC-BY 3.0 license",
          "license": "http://creativecommons.org/licenses/by/3.0/"
        },
        "nuts_level1": {
          "code": null,
          "name": null
        },
        "nuts_level2": {
          "code": null,
          "name": null
        },
        "nuts_level3": {
          "code": null,
          "name": null
        }
      },
      "postcode": null,
      "primary": false,
      "line": null,
      "country_geonames_id": null
    }
  ],
  "links": [
    "https://mgcollegearmori.ac.in"
  ],
  "aliases": [
    "M. G. Arts, Science & Late N. P. Commerce College",
    "M.G. College, Armori",
    "Mahatma Gandhi Arts, Science and Late N. P. Commerce College",
    "Mahatma Gandhi College, Armori"
  ],
  "acronyms": [
    "MGCA"
  ],
  "status": "active",
  "wikipedia_url": null,
  "labels": [],
  "country": {
    "country_name": "India",
    "country_code": "IN"
  },
  "external_ids": {
    "ISNI": {
      "all": [
        "0000 0004 8351 5025"
      ],
      "preferred": "0000 0004 8351 5025"
    }
  }
}