{
  "id": "https://ror.org/047w75g40",
  "name": "International Islamic University, Islamabad",
  "email_address": null,
  "ip_addresses": [],
  "established": 1980,
  "types": [
    "Education"
  ],
  "relationships": [],
  "addresses": [
    {
      "lat": 33.72148,
      "lng": 73.04329,
      "state": null,
      "state_code": null,
      "city": "Islamabad",
      "geonames_city": {
        "id": 1176615,
        "city": "Islamabad",
        "geonames_admin1": {
          "ascii_name": null,
          "code": "PK.IS",
          "id": null,
          "name": "Islamabad"
        },
        "geonames_admin2": {
          "ascii_name": null,
          "code": null,
          "id": null,
          "name": null
        },
        "license": {
          "attribution": "Data from geonames.org under a CC-BY 3.0 license",
          "license": "http://creativecommons.org/licenses/by/3.0/"
        },
        "nuts_level1": {
          "code": null,
          "name": null
        },
        "nuts_level2": {
          "code": null,
          "name": null
        },
        "nuts_level3": {
          "code": null,
          "name": null
        }
      },
      "postcode": null,
      "primary": false,
      "line": null,
      "country_geonames_id": null
    }
  ],
  "links": [
    "https://iiu.edu.pk/default.htm"
  ],
  "aliases": [],
  "acronyms": [
    "IIUI"
  ],
  "status": "active",
  "wikipedia_url": "http://en.wikipedia.org/wiki/International_Islamic_University,_Islamabad",
  "labels": [
    {
      "label": "بين الاقوامی اسلامی يونيورسٹی اسلام آباد‎",
      "iso639": "ur"
    }
  ],
  "country": {
    "country_name": "Pakistan",
    "country_code": "PK"
  },
  "external_ids": {
    "FundRef": {
      "all": [
        "100021121"
      ],
      "preferred": "100021121"
    },
    "GRID": {
      "all": "grid.411727.6",
      "preferred": "grid.411727.6"
    },
    "ISNI": {
      "all": [
        "0000 0001 2201 6036"
      ],
      "preferred": null
    },
    "Wikidata": {
      "all": [
        "Q3918518"
      ],
      "preferred": null
    }
  }
}