{
  "id": "https://ror.org/03dgrff29",
  "name": "Instituto Tecnológico Superior de Loreto",
  "email_address": null,
  "ip_addresses": [],
  "established": null,
  "types": [
    "Education"
  ],
  "relationships": [
    {
      "label": "National Technological Institute of Mexico",
      "type": "Parent",
      "id": "https://ror.org/00davry38"
    }
  ],
  "addresses": [
    {
      "lat": 22.27248,
      "lng": -101.98898,
      "state": null,
      "state_code": null,
      "city": "Loreto",
      "geonames_city": {
        "id": 3998291,
        "city": "Loreto",
        "geonames_admin1": {
          "ascii_name": null,
          "code": null,
          "id": null,
          "name": null
        },
        "geonames_admin2": {
          "ascii_name": null,
          "code": null,
          "id": null,
          "name": null
        },
        "license": {
          "attribution": "Data from geonames.org under a CC-BY 3.0 license",
          "license": "http://creativecommons.org/licenses/by/3.0/"
        },
        "nuts_level1": {
          "code": null,
          "name": null
        },
        "nuts_level2": {
          "code": null,
          "name": null
        },
        "nuts_level3": {
          "code": null,
          "name": null
        }
      },
      "postcode": null,
      "primary": false,
      "line": null,
      "country_geonames_id": null
    }
  ],
  "links": [
    "https://itsloreto.edu.mx"
  ],
  "aliases": [
    "ITS Loreto",
    "TecNM Campus Loreto",
    "Tecnológico Nacional de México Campus Loreto"
  ],
  "acronyms": [],
  "status": "active",
  "wikipedia_url": null,
  "labels": [],
  "country": {
    "country_name": "Mexico",
    "country_code": "MX"
  },
  "external_ids": {
    "ISNI": {
      "all": [
        "0000 0004 1770 1161"
      ],
      "preferred": "0000 0004 1770 1161"
    }
  }
}