{
  "id": "https://ror.org/05nn4ph13",
  "name": "Hata Kenmin Hospital",
  "email_address": null,
  "ip_addresses": [],
  "established": null,
  "types": [
    "Healthcare"
  ],
  "relationships": [],
  "addresses": [
    {
      "lat": 32.93333,
      "lng": 132.73333,
      "state": null,
      "state_code": null,
      "city": "Sukumo",
      "geonames_city": {
        "id": 1851462,
        "city": "Sukumo",
        "geonames_admin1": {
          "ascii_name": null,
          "code": "JP.39",
          "id": null,
          "name": "Kochi"
        },
        "geonames_admin2": {
          "ascii_name": null,
          "code": null,
          "id": null,
          "name": null
        },
        "license": {
          "attribution": "Data from geonames.org under a CC-BY 3.0 license",
          "license": "http://creativecommons.org/licenses/by/3.0/"
        },
        "nuts_level1": {
          "code": null,
          "name": null
        },
        "nuts_level2": {
          "code": null,
          "name": null
        },
        "nuts_level3": {
          "code": null,
          "name": null
        }
      },
      "postcode": null,
      "primary": false,
      "line": null,
      "country_geonames_id": null
    }
  ],
  "links": [
    "https://www.pref.kochi.lg.jp/hata/"
  ],
  "aliases": [],
  "acronyms": [],
  "status": "active",
  "wikipedia_url": null,
  "labels": [
    {
      "label": "高知県立幡多けんみん病院",
      "iso639": "ja"
    }
  ],
  "country": {
    "country_name": "Japan",
    "country_code": "JP"
  },
  "external_ids": {}
}