{
  "id": "https://ror.org/04hke8425",
  "name": "Laboratoire de Biologie du Développement de Villefranche-sur-Mer",
  "email_address": null,
  "ip_addresses": [],
  "established": 1999,
  "types": [
    "Facility"
  ],
  "relationships": [
    {
      "label": "Institut des Sciences Biologiques",
      "type": "Parent",
      "id": "https://ror.org/00rydyx93"
    },
    {
      "label": "Sorbonne Université",
      "type": "Parent",
      "id": "https://ror.org/02en5vm52"
    },
    {
      "label": "Institut de la Mer de Villefranche",
      "type": "Parent",
      "id": "https://ror.org/05jpad840"
    },
    {
      "label": "Centre National de la Recherche Scientifique",
      "type": "Parent",
      "id": "https://ror.org/02feahw73"
    }
  ],
  "addresses": [
    {
      "lat": 43.70392,
      "lng": 7.31088,
      "state": null,
      "state_code": null,
      "city": "Villefranche-sur-Mer",
      "geonames_city": {
        "id": 2968749,
        "city": "Villefranche-sur-Mer",
        "geonames_admin1": {
          "ascii_name": null,
          "code": "FR.PAC",
          "id": null,
          "name": "Provence-Alpes-Côte d'Azur"
        },
        "geonames_admin2": {
          "ascii_name": null,
          "code": null,
          "id": null,
          "name": null
        },
        "license": {
          "attribution": "Data from geonames.org under a CC-BY 3.0 license",
          "license": "http://creativecommons.org/licenses/by/3.0/"
        },
        "nuts_level1": {
          "code": null,
          "name": null
        },
        "nuts_level2": {
          "code": null,
          "name": null
        },
        "nuts_level3": {
          "code": null,
          "name": null
        }
      },
      "postcode": null,
      "primary": false,
      "line": null,
      "country_geonames_id": null
    }
  ],
  "links": [
    "https://lbdv.imev-mer.fr"
  ],
  "aliases": [],
  "acronyms": [
    "LBDV"
  ],
  "status": "active",
  "wikipedia_url": null,
  "labels": [
    {
      "label": "Villefranche-sur-mer Developmental Biology Laboratory",
      "iso639": "en"
    }
  ],
  "country": {
    "country_name": "France",
    "country_code": "FR"
  },
  "external_ids": {
    "GRID": {
      "all": "grid.463888.9",
      "preferred": "grid.463888.9"
    },
    "ISNI": {
      "all": [
        "0000 0004 0452 5939"
      ],
      "preferred": null
    },
    "Wikidata": {
      "all": [
        "Q30262270"
      ],
      "preferred": "Q30262270"
    }
  }
}