{
  "id": "https://ror.org/05j7gyw58",
  "name": "Université des Sciences et de Technologie d'Ati",
  "email_address": null,
  "ip_addresses": [],
  "established": 2008,
  "types": [
    "Education"
  ],
  "relationships": [],
  "addresses": [
    {
      "lat": 13.2138,
      "lng": 18.3393,
      "state": null,
      "state_code": null,
      "city": "Ati",
      "geonames_city": {
        "id": 2436400,
        "city": "Ati",
        "geonames_admin1": {
          "ascii_name": null,
          "code": "TD.BA",
          "id": null,
          "name": "Batha"
        },
        "geonames_admin2": {
          "ascii_name": null,
          "code": null,
          "id": null,
          "name": null
        },
        "license": {
          "attribution": "Data from geonames.org under a CC-BY 3.0 license",
          "license": "http://creativecommons.org/licenses/by/3.0/"
        },
        "nuts_level1": {
          "code": null,
          "name": null
        },
        "nuts_level2": {
          "code": null,
          "name": null
        },
        "nuts_level3": {
          "code": null,
          "name": null
        }
      },
      "postcode": null,
      "primary": false,
      "line": null,
      "country_geonames_id": null
    }
  ],
  "links": [],
  "aliases": [],
  "acronyms": [
    "USTA"
  ],
  "status": "active",
  "wikipedia_url": "https://fr.wikipedia.org/wiki/Universit%C3%A9_des_sciences_et_de_technologie_d%27Ati",
  "labels": [
    {
      "label": "Ati University of Science and Technology",
      "iso639": "en"
    }
  ],
  "country": {
    "country_name": "Chad",
    "country_code": "TD"
  },
  "external_ids": {
    "Wikidata": {
      "all": [
        "Q3551736"
      ],
      "preferred": "Q3551736"
    }
  }
}