{
  "id": "https://ror.org/0408cjw96",
  "name": "Bamidele Olumilua University of Education, Science and Technology",
  "email_address": null,
  "ip_addresses": [],
  "established": 2020,
  "types": [
    "Education"
  ],
  "relationships": [],
  "addresses": [
    {
      "lat": 7.49748,
      "lng": 5.23041,
      "state": null,
      "state_code": null,
      "city": "Ikere-Ekiti",
      "geonames_city": {
        "id": 2338287,
        "city": "Ikere-Ekiti",
        "geonames_admin1": {
          "ascii_name": null,
          "code": "NG.EK",
          "id": null,
          "name": "Ekiti State"
        },
        "geonames_admin2": {
          "ascii_name": null,
          "code": null,
          "id": null,
          "name": null
        },
        "license": {
          "attribution": "Data from geonames.org under a CC-BY 3.0 license",
          "license": "http://creativecommons.org/licenses/by/3.0/"
        },
        "nuts_level1": {
          "code": null,
          "name": null
        },
        "nuts_level2": {
          "code": null,
          "name": null
        },
        "nuts_level3": {
          "code": null,
          "name": null
        }
      },
      "postcode": null,
      "primary": false,
      "line": null,
      "country_geonames_id": null
    }
  ],
  "links": [
    "https://portal.bouesti.edu.ng"
  ],
  "aliases": [],
  "acronyms": [
    "BOUESTI"
  ],
  "status": "active",
  "wikipedia_url": null,
  "labels": [
    {
      "label": "Bamidele Olumilua University of Education, Science and Technology, Ikere-Ekiti",
      "iso639": "en"
    }
  ],
  "country": {
    "country_name": "Nigeria",
    "country_code": "NG"
  },
  "external_ids": {}
}