{
  "id": "https://ror.org/01zk01k31",
  "name": "City of Portsmouth College",
  "email_address": null,
  "ip_addresses": [],
  "established": 2021,
  "types": [
    "Education"
  ],
  "relationships": [
    {
      "label": "Highbury College",
      "type": "Predecessor",
      "id": "https://ror.org/01zz9ka42"
    },
    {
      "label": "Portsmouth College",
      "type": "Predecessor",
      "id": "https://ror.org/05gdfay69"
    }
  ],
  "addresses": [
    {
      "lat": 50.79899,
      "lng": -1.09125,
      "state": null,
      "state_code": null,
      "city": "Portsmouth",
      "geonames_city": {
        "id": 2639996,
        "city": "Portsmouth",
        "geonames_admin1": {
          "ascii_name": null,
          "code": null,
          "id": null,
          "name": null
        },
        "geonames_admin2": {
          "ascii_name": null,
          "code": null,
          "id": null,
          "name": null
        },
        "license": {
          "attribution": "Data from geonames.org under a CC-BY 3.0 license",
          "license": "http://creativecommons.org/licenses/by/3.0/"
        },
        "nuts_level1": {
          "code": null,
          "name": null
        },
        "nuts_level2": {
          "code": null,
          "name": null
        },
        "nuts_level3": {
          "code": null,
          "name": null
        }
      },
      "postcode": null,
      "primary": false,
      "line": null,
      "country_geonames_id": null
    }
  ],
  "links": [
    "https://www.city-of-portsmouth-college.ac.uk"
  ],
  "aliases": [],
  "acronyms": [],
  "status": "active",
  "wikipedia_url": null,
  "labels": [],
  "country": {
    "country_name": "United Kingdom",
    "country_code": "GB"
  },
  "external_ids": {}
}